Workbook

Sheet Dashboard
B2: DEL Commercial Department — Management Dashboard
B3: Auto-calculated from the Opportunity Pipeline & Commercial Operations trackers.
B5: PIPELINE OVERVIEW
B6: Total Opportunities | D6: Active | F6: Converted | H6: Nurture | J6: Deferred | L6: Rejected / Dead
B7: =COUNTA('Opportunity Pipeline Tracker'!$B$4:$B$26) -> 22 | D7: =COUNTIF('Opportunity Pipeline Tracker'!$N$4:$N$26,"Active") -> 13 | F7: =COUNTIF('Opportunity Pipeline Tracker'!$N$4:$N$26,"Converted") -> 7 | H7: =COUNTIF('Opportunity Pipeline Tracker'!$N$4:$N$26,"Nurture") -> 0 | J7: =COUNTIF('Opportunity Pipeline Tracker'!$N$4:$N$26,"Deferred") -> 0 | L7: =COUNTIF('Opportunity Pipeline Tracker'!$N$4:$N$26,"Rejected")+COUNTIF('Opportunity Pipeline Tracker'!$N$4:$N$26,"Dead / Silent")+COUNTIF('Opportunity Pipeline Tracker'!$N$4:$N$26,"Failed Knockout") -> 2
B9: PIPELINE HEALTH
B10: Awaiting Customer Data | D10: Awaiting Internal Review | F10: Overdue / Delayed Actions | H10: Conversion Rate | J10: Avg Cycle Time (days) | L10: Cluster Potential
B11: =COUNTIF('Opportunity Pipeline Tracker'!$L$4:$L$26,"NDA / Data Request") -> 1 | D11: =COUNTIF('Opportunity Pipeline Tracker'!$Z$4:$Z$26,"Yes") -> 4 | F11: =SUMPRODUCT(('Opportunity Pipeline Tracker'!$U$4:$U$26<>"")*(ISNUMBER('Opportunity Pipeline Tracker'!$U$4:$U$26))*('Opportunity Pipeline Tracker'!$U$4:$U$26<TODAY())*('Opportunity Pipeline Tracker'!$N$4:$N$26<>"Converted")*('Opportunity Pipeline Tracker'!$N$4:$N$26<>"Rejected")*('Opportunity Pipeline Tracker'!$N$4:$N$26<>"Dead / Silent")) -> 0 | H11: =IFERROR(COUNTIF('Opportunity Pipeline Tracker'!$N$4:$N$26,"Converted")/COUNTA('Opportunity Pipeline Tracker'!$B$4:$B$26),0) -> 0.31818182 | J11: =IFERROR(ROUND(AVERAGE('Opportunity Pipeline Tracker'!$AE$4:$AE$26),0),"-") -> - | L11: =COUNTIF('Opportunity Pipeline Tracker'!$N$4:$N$26,"Cluster Potential") -> 0
B13: COMMERCIAL OPERATIONS
B14: Contracts Expiring ≤ 90 days | D14: Contracts Expired | F14: Tariff Reviews Overdue | H14: KYC Pending | J14: High-Priority Issues | L14: Customers in Commercial Ops
B15: =SUMPRODUCT(('Commercial Operations Tracker'!$F$4:$F$12<>"")*(ISNUMBER('Commercial Operations Tracker'!$F$4:$F$12))*('Commercial Operations Tracker'!$F$4:$F$12>=0)*('Commercial Operations Tracker'!$F$4:$F$12<=90)) -> 0 | D15: =COUNTIF('Commercial Operations Tracker'!$G$4:$G$12,"Overdue")+COUNTIF('Commercial Operations Tracker'!$C$4:$C$12,"PPA (addendum in progress)")*0+COUNTIF('Commercial Operations Tracker'!$E$4:$E$12,"<"&TODAY()) -> 1 | F15: =COUNTIF('Commercial Operations Tracker'!$I$4:$I$12,"Overdue") -> 1 | H15: =COUNTIF('Commercial Operations Tracker'!$J$4:$J$12,"Pending")+COUNTIF('Commercial Operations Tracker'!$J$4:$J$12,"In Progress")+COUNTIF('Commercial Operations Tracker'!$J$4:$J$12,"Not Started") -> 0 | J15: =COUNTIF('Commercial Operations Tracker'!$T$4:$T$12,"High") -> 1 | L15: =COUNTA('Commercial Operations Tracker'!$A$4:$A$12) -> 8
B17: OPPORTUNITIES BY BUSINESS LINE | E17: OPPORTUNITIES BY STAGE
B18: Business Line | C18: Count | E18: Stage | F18: Count
B19: Power | C19: =COUNTIF('Opportunity Pipeline Tracker'!$D$4:$D$26,"Power") -> 12 | E19: Lead Received | F19: =COUNTIF('Opportunity Pipeline Tracker'!$L$4:$L$26,"Lead Received") -> 0
B20: Captive Power | C20: =COUNTIF('Opportunity Pipeline Tracker'!$D$4:$D$26,"Captive Power") -> 5 | E20: Lead Logged | F20: =COUNTIF('Opportunity Pipeline Tracker'!$L$4:$L$26,"Lead Logged") -> 0
B21: Gas Retail | C21: =COUNTIF('Opportunity Pipeline Tracker'!$D$4:$D$26,"Gas Retail") -> 3 | E21: Initial Screening | F21: =COUNTIF('Opportunity Pipeline Tracker'!$L$4:$L$26,"Initial Screening") -> 0
B22: Autogas/CNG | C22: =COUNTIF('Opportunity Pipeline Tracker'!$D$4:$D$26,"Autogas/CNG") -> 1 | E22: Knockout Test | F22: =COUNTIF('Opportunity Pipeline Tracker'!$L$4:$L$26,"Knockout Test") -> 1
B23: Collaboration | C23: =COUNTIF('Opportunity Pipeline Tracker'!$D$4:$D$26,"Collaboration") -> 1 | E23: NDA / Data Request | F23: =COUNTIF('Opportunity Pipeline Tracker'!$L$4:$L$26,"NDA / Data Request") -> 1
B24: Venture | C24: =COUNTIF('Opportunity Pipeline Tracker'!$D$4:$D$26,"Venture") -> 0 | E24: Site Reconnaissance | F24: =COUNTIF('Opportunity Pipeline Tracker'!$L$4:$L$26,"Site Reconnaissance") -> 2
E25: Energy Audit | F25: =COUNTIF('Opportunity Pipeline Tracker'!$L$4:$L$26,"Energy Audit") -> 1
B26: OWNER WORKLOAD (open items) | E26: Indicative Tariff / Solution | F26: =COUNTIF('Opportunity Pipeline Tracker'!$L$4:$L$26,"Indicative Tariff / Solution") -> 4
B27: Owner | C27: Items | E27: Proposal / Term Sheet | F27: =COUNTIF('Opportunity Pipeline Tracker'!$L$4:$L$26,"Proposal / Term Sheet") -> 3
B28: Mide (Commercial Manager) | C28: =COUNTIF('Opportunity Pipeline Tracker'!$T$4:$T$26,"Mide (Commercial Manager)")+COUNTIF('Commercial Operations Tracker'!$P$4:$P$12,"Mide (Commercial Manager)") -> 0 | E28: Negotiation | F28: =COUNTIF('Opportunity Pipeline Tracker'!$L$4:$L$26,"Negotiation") -> 2
B29: Temitope | C29: =COUNTIF('Opportunity Pipeline Tracker'!$T$4:$T$26,"Temitope")+COUNTIF('Commercial Operations Tracker'!$P$4:$P$12,"Temitope") -> 1 | E29: Contract Signing | F29: =COUNTIF('Opportunity Pipeline Tracker'!$L$4:$L$26,"Contract Signing") -> 1
B30: Damilare | C30: =COUNTIF('Opportunity Pipeline Tracker'!$T$4:$T$26,"Damilare")+COUNTIF('Commercial Operations Tracker'!$P$4:$P$12,"Damilare") -> 0 | E30: Onboarding / KYC | F30: =COUNTIF('Opportunity Pipeline Tracker'!$L$4:$L$26,"Onboarding / KYC") -> 0
B31: Abdullateef | C31: =COUNTIF('Opportunity Pipeline Tracker'!$T$4:$T$26,"Abdullateef")+COUNTIF('Commercial Operations Tracker'!$P$4:$P$12,"Abdullateef") -> 0 | E31: Implementation | F31: =COUNTIF('Opportunity Pipeline Tracker'!$L$4:$L$26,"Implementation") -> 0
B32: BD Team | C32: =COUNTIF('Opportunity Pipeline Tracker'!$T$4:$T$26,"BD Team")+COUNTIF('Commercial Operations Tracker'!$P$4:$P$12,"BD Team") -> 14 | E32: Revenue Generation | F32: =COUNTIF('Opportunity Pipeline Tracker'!$L$4:$L$26,"Revenue Generation") -> 7
B33: Commercial Ops | C33: =COUNTIF('Opportunity Pipeline Tracker'!$T$4:$T$26,"Commercial Ops")+COUNTIF('Commercial Operations Tracker'!$P$4:$P$12,"Commercial Ops") -> 15
B34: Legal | C34: =COUNTIF('Opportunity Pipeline Tracker'!$T$4:$T$26,"Legal")+COUNTIF('Commercial Operations Tracker'!$P$4:$P$12,"Legal") -> 0
B35: Technical | C35: =COUNTIF('Opportunity Pipeline Tracker'!$T$4:$T$26,"Technical")+COUNTIF('Commercial Operations Tracker'!$P$4:$P$12,"Technical") -> 0
B36: Finance | C36: =COUNTIF('Opportunity Pipeline Tracker'!$T$4:$T$26,"Finance")+COUNTIF('Commercial Operations Tracker'!$P$4:$P$12,"Finance") -> 0

Sheet Lists & Data Validation
B2: Dropdown Lists & Data Validation
B4: BusinessLine | C4: OppType | D4: Source | E4: Stage | F4: Knockout | G4: Classification | H4: HML | I4: Owner | J4: YesNo | K4: Priority | L4: Rev. Gen. Status | M4: RevImpact | N4: ContractType | O4: ContractStatus | P4: RenewalStatus | Q4: TariffStatus | R4: KYC | S4: Onboarding | T4: Metering | U4: Payment
B5: Power | C5: Non- tender | D5: Direct BD | E5: Lead Received/Logged | F5: Pass | G5: Active | H5: High | I5: Mide (Commercial Manager) | J5: Yes | K5: High | L5: On Track | M5: High | N5: PPA | O5: Active | P5: Not Due | Q5: Up to Date | R5: Complete | S5: Complete | T5: Installed & Commissioned | U5: Current
B6: Captive Power | C6: Tender | D6: Referral - Existing customers | E6: Screening (Knockout Test) | F6: Fail | G6: Deferred | H6: Medium | I6: Temitope | J6: No | K6: Medium | L6: At Risk | M6: Medium | N6: GSPA | O6: Expiring Soon | P6: Due Soon | Q6: Due | R6: In Progress | S6: In Progress | T6: Installed | U6: Minor Arrears
B7: Gas Retail | C7: Cluster / Strategic | D7: Third-Party Finder | E7: NDA / Data Request | F7: Pending | G7: Rejected | H7: Low | I7: Damilare | K7: Low | L7: Delayed | M7: Low | N7: Captive Power Agreement | O7: Expired | P7: Overdue | Q7: Overdue | R7: Pending | S7: Pending | T7: Pending | U7: In Arrears
B8: Autogas/CNG | C8: Venture (JVs, Co-Investment, Consortium) | D8: Existing Customer Expansion | E8: Site Reconnaissance | G8: Converted | I8: Abdullateef | L8: Blocked | M8: None | N8: Term Sheet | O8: In Negotiation | P8: In Progress | Q8: Under Review | R8: Not Started | S8: Not Started | T8: Not Started | U8: On Prepayment
B9: Collaboration | D9: Strategic Partnership | E9: Energy Audit | G9: Dead | I9: BD Team | L9: On Hold | N9: Autogas Supply Agreement | O9: Draft | P9: Renewed | Q9: Applied | U9: N/A
B10: Venture | D10: Board | E10: Proposal / Term Sheet | G10: Failed Knockout | I10: Commercial Ops | L10: Complete | N10: MOU / NDA | O10: Renewal Due
D11: Internal (DEL Non- comm.) | E11: Negotiation | I11: Legal | N11: Not Started | O11: Not Started
E12: Contract Signing | I12: Technical
E13: Onboarding / KYC | I13: Finance
E14: Implementation
E15: Revenue Generation
B18: These lists feed the dropdowns and conditional formatting across all sheets. Edit a list here to update the choices everywhere. Add new owners, business lines or stages as needed.

Sheet Opportunity Pipeline Tracker
B2: DEL Commercial Department — Opportunity Pipeline Tracker
B3: Opportunity ID | C3: Customer / Project Name | D3: Business Line | E3: Opportunity Type | F3: Source | G3: Finder / Originator | H3: Location | I3: Estimated Load / Demand | J3: Est. Revenue Potential (₦/yr) | K3: Date Received | L3: Current Stage | M3: Knockout Result | N3: Classification | O3: Commercial Readiness | P3: Technical Feasibility | Q3: Strategic Fit | R3: Key Issue / Delay | S3: Next Action | T3: Action Owner | U3: Expected Conver. Date | V3: Last Engagement Date | W3: Days Since Last Engagement | X3: Probability of Conversion | Y3: Status Comment | Z3: Mgmt Decision Required? | AA3: Support Required | AB3: Final Outcome | AC3: Reason Closed / Deferred | AD3: Final Outcome Date | AE3: Cycle Time (days)
B4: OPP-001 | C4: Stanbic IBTC (WCC) | D4: Power | F4: Direct BD | I4: 750 | L4: Revenue Generation | M4: Pass | N4: Converted | O4: High | P4: High | Q4: High | T4: Commercial Ops | W4: =IF(V4="","",TODAY()-V4) | X4: 1 | Y4: Operating. | Z4: No | AE4: =IF(AND(K4<>"",AD4<>""),AD4-K4,"")
B5: OPP-002 | C5: UBA PLC | D5: Power | E5: Non-tender | F5: Direct BD | I5: 2700 | L5: Negotiation | M5: Pass | N5: Active | O5: High | P5: High | Q5: High | R5: PPA addendum (tariff terms) pending | S5: Conclude PPA addendum on tariff & commercial terms | T5: BD Team | W5: =IF(V5="","",TODAY()-V5) | X5: 0.85 | Y5: Negotiating an addendum to the PPA with tariff and other commercial considerations. | Z5: Yes | AA5: Legal, Commercial | AE5: =IF(AND(K5<>"",#REF!<>""),#REF!-K5,"") -> #REF!
B6: OPP-003 | C6: Sterling Bank PLC | D6: Power | E6: Non-tender | F6: Direct BD | I6: 750 | L6: Indicative Tariff / Solution | M6: Pass | N6: Dead / Silent | O6: Low | P6: High | Q6: Medium | R6: Backup-supply scope; IPL2 connection | S6: Progress backup-supply (~4hr) renegotiation | T6: BD Team | W6: =IF(V6="","",TODAY()-V6) | X6: 0.35 | Y6: Early-stage renegotiation. Customer connected to IPL2. Requesting backup supply (c.4hrs). | Z6: No | AE6: =IF(AND(K6<>"",#REF!<>""),#REF!-K6,"") -> #REF!
B7: OPP-004 | C7: Stanbic IBTC (Windsor Building) | D7: Power | E7: Non-tender | F7: Direct BD | I7: 1000 | L7: Indicative Tariff / Solution | M7: Pass | N7: Active | O7: Medium | P7: High | Q7: Medium | R7: Contract novation pending | S7: Complete contract novation; advance commercial terms | T7: BD Team | W7: =IF(V7="","",TODAY()-V7) | X7: 0.35 | Y7: Completion of the contract novation and commercial discussions are in progress. | Z7: No | AE7: =IF(AND(K7<>"",#REF!<>""),#REF!-K7,"") -> #REF!
B8: OPP-005 | C8: Periwinkle Residences | D8: Power | E8: Non-tender | F8: Direct BD | I8: 250 | L8: Revenue Generation | M8: Pass | N8: Converted | O8: High | P8: High | Q8: High | T8: Commercial Ops | W8: =IF(V8="","",TODAY()-V8) | X8: 1 | Y8: Operating. | Z8: No | AE8: =IF(AND(K8<>"",#REF!<>""),#REF!-K8,"") -> #REF!
B9: OPP-006 | C9: Orange Island Residences | D9: Power | E9: Non-tender | F9: Direct BD | I9: 100 | L9: Revenue Generation | M9: Pass | N9: Converted | O9: High | P9: High | Q9: High | T9: Commercial Ops | W9: =IF(V9="","",TODAY()-V9) | X9: 1 | Y9: Operating. | Z9: No | AE9: =IF(AND(K9<>"",#REF!<>""),#REF!-K9,"") -> #REF!
B10: OPP-007 | C10: Purple Mall | D10: Power | E10: Non-tender | F10: Direct BD | I10: 500 | L10: Proposal / Term Sheet | M10: Pass | N10: Active | O10: Medium | P10: High | Q10: Medium | S10: Advance commercial discussions toward term sheet | T10: BD Team | W10: =IF(V10="","",TODAY()-V10) | X10: 0.5 | Y10: Commercial discussions are in progress. | Z10: No | AE10: =IF(AND(K10<>"",#REF!<>""),#REF!-K10,"") -> #REF!
B11: OPP-008 | C11: Sweetco Power | D11: Captive Power | E11: Non-tender | F11: Direct BD | I11: 1500 | L11: Revenue Generation | M11: Pass | N11: Converted | O11: High | P11: High | Q11: High | R11: Contract expired; tariff escalation overdue | S11: Prepare contract renewal & tariff escalation plan | T11: Commercial Ops | W11: =IF(V11="","",TODAY()-V11) | X11: 1 | Y11: Operating. | Z11: Yes | AA11: Legal (contract), Commercial (tariff) | AB11: Converted – Operating (renewal due) | AE11: =IF(AND(K11<>"",#REF!<>""),#REF!-K11,"") -> #REF!
B12: OPP-009 | C12: Renaissance | D12: Power | E12: Non-tender | F12: Direct BD | I12: 2000 | L12: Negotiation | M12: Pass | N12: Active | O12: Medium | P12: High | Q12: High | R12: PPA execution pending | S12: Finalise and sign PPA (target May 2026) | T12: BD Team | W12: =IF(V12="","",TODAY()-V12) | X12: 0.6 | Y12: PPA to be signed in May 2026. | Z12: No | AD12: 46173 | AE12: =IF(AND(K12<>"",#REF!<>""),#REF!-K12,"") -> #REF!
B13: OPP-010 | C13: Re-insurance House | D13: Power | E13: Non-tender | F13: Direct BD | I13: 3000 | L13: Indicative Tariff / Solution | M13: Pass | N13: Active | O13: Medium | P13: High | Q13: High | S13: Use completed energy audit to issue indicative solution/tariff | T13: BD Team | W13: =IF(V13="","",TODAY()-V13) | X13: 0.35 | Y13: Energy audit completed, commercial discussions are in progress. | Z13: No | AE13: =IF(AND(K13<>"",#REF!<>""),#REF!-K13,"") -> #REF!
B14: OPP-011 | C14: Lekki Port | D14: Captive Power | E14: Tender | F14: Direct BD | I14: 1000 | L14: Proposal / Term Sheet | M14: Pending | N14: Active | O14: Medium | P14: Medium | Q14: Medium | R14: Tender decision pending | S14: Await tender outcome; sustain technical alignment | T14: BD Team | W14: =IF(V14="","",TODAY()-V14) | X14: 0.2 | Y14: Bid submission completed, technical alignment discussion completed. | Z14: No | AE14: =IF(AND(K14<>"",#REF!<>""),#REF!-K14,"") -> #REF!
B15: OPP-012 | C15: FCMB | D15: Power | E15: Non-tender | F15: Direct BD | G15: CEO | I15: 100000 | L15: Indicative Tariff / Solution | M15: Pass | N15: Active | O15: Medium | P15: High | Q15: High | R15: Validate scope/scale (portfolio) | S15: Validate scope and progress commercial discussions | T15: BD Team | W15: =IF(V15="","",TODAY()-V15) | X15: 0.35 | Y15: Commercial discussions are in progress. | Z15: Yes | AA15: Technical (scope) | AE15: =IF(AND(K15<>"",#REF!<>""),#REF!-K15,"") -> #REF!
B16: OPP-013 | C16: NRC | D16: Captive Power | E16: Non-tender | F16: Board | G16: Anergi | I16: 6000 | L16: Knockout Test | M16: Pass | N16: Rejected | O16: Low | P16: Medium | Q16: High | S16: Deferred — revisit if requirements change | T16: BD Team | W16: =IF(V16="","",TODAY()-V16) | X16: 0.05 | Y16: Stepped down. | Z16: No | AB16: Deferred | AC16: Customer stepped down | AE16: =IF(AND(K16<>"",#REF!<>""),#REF!-K16,"") -> #REF!
B17: OPP-014 | C17: Natcom | D17: Power | E17: Non-tender | F17: Direct BD | G17: Viathan | I17: 200 | L17: Energy Audit | M17: Pending | N17: Active | O17: Low | P17: High | Q17: Medium | S17: Complete energy audit | T17: BD Team | W17: =IF(V17="","",TODAY()-V17) | X17: 0.2 | Y17: Energy Audit in progress. | Z17: No | AE17: =IF(AND(K17<>"",#REF!<>""),#REF!-K17,"") -> #REF!
B18: OPP-015 | C18: Pillar Oil | D18: Captive Power | E18: Non-tender | F18: Third-Party Finder | G18: QR Media | I18: 200 | L18: Site Reconnaissance | M18: Pending | N18: Active | O18: Low | P18: Medium | Q18: Medium | S18: Progress techno-commercial discussions; schedule energy audit | T18: BD Team | W18: =IF(V18="","",TODAY()-V18) | X18: 0.15 | Y18: Techno-commercial discussions. | Z18: No | AE18: =IF(AND(K18<>"",#REF!<>""),#REF!-K18,"") -> #REF!
B19: OPP-016 | C19: Tranquil and Quest Hospital | D19: Power | E19: Non-tender | F19: Direct BD | I19: 150 | L19: Site Reconnaissance | M19: Pending | N19: Active | O19: Low | P19: High | Q19: Medium | S19: Convert reconnaissance into energy audit | T19: BD Team | W19: =IF(V19="","",TODAY()-V19) | X19: 0.15 | Y19: Reconnaissance survey conducted. | Z19: No | AE19: =IF(AND(K19<>"",#REF!<>""),#REF!-K19,"") -> #REF!
B20: OPP-017 | C20: Lakowe Resort | D20: Captive Power | E20: Tender | F20: Direct BD | I20: 1000 | L20: Proposal / Term Sheet | M20: Pending | N20: Active | O20: Low | P20: Medium | Q20: Medium | R20: Tender decision pending | S20: Await bid outcome | T20: BD Team | W20: =IF(V20="","",TODAY()-V20) | X20: 0.2 | Y20: Bid submission completed. | Z20: No | AE20: =IF(AND(K20<>"",#REF!<>""),#REF!-K20,"") -> #REF!
B21: OPP-018 | C21: Sweetco Gas | D21: Gas Retail | E21: Non-tender | F21: Direct BD | L21: Revenue Generation | M21: Pass | N21: Converted | O21: High | P21: High | Q21: High | T21: Commercial Ops | W21: =IF(V21="","",TODAY()-V21) | X21: 1 | Y21: Operating (Gas to Power and Heat). | Z21: No | AB21: Converted – Operating | AE21: =IF(AND(K21<>"",#REF!<>""),#REF!-K21,"") -> #REF!
B22: OPP-019 | C22: Starium Detergents FZE | D22: Gas Retail | E22: Non-tender | F22: Direct BD | L22: Revenue Generation | M22: Pass | N22: Converted | O22: High | P22: High | Q22: High | T22: Commercial Ops | W22: =IF(V22="","",TODAY()-V22) | X22: 1 | Y22: Operating (Gas to Power and Heat). | Z22: No | AB22: Converted – Operating | AE22: =IF(AND(K22<>"",#REF!<>""),#REF!-K22,"") -> #REF!
B23: OPP-020 | C23: Rumbu Industries Limited | D23: Gas Retail | E23: Non-tender | F23: Direct BD | L23: Revenue Generation | M23: Pass | N23: Converted | O23: High | P23: High | Q23: High | T23: Commercial Ops | W23: =IF(V23="","",TODAY()-V23) | X23: 1 | Y23: Operating (Gas to Power). | Z23: No | AB23: Converted – Operating | AE23: =IF(AND(K23<>"",#REF!<>""),#REF!-K23,"") -> #REF!
B24: OPP-021 | C24: Dangote | D24: Autogas/CNG | E24: Non-tender | F24: Strategic Partnership | G24: Viathan | L24: Contract Signing | M24: Pass | N24: Active | O24: High | P24: High | Q24: High | S24: Advance autogas opportunity with partner (Viathan) toward contract | T24: BD Team | W24: =IF(V24="","",TODAY()-V24) | X24: 0.75 | Y24: A new opportunity we are exploring with Viathan. | Z24: No | AE24: =IF(AND(K24<>"",#REF!<>""),#REF!-K24,"") -> #REF!
B25: OPP-022 | C25: Transgrid / IBEDC Cluster | D25: Collaboration | E25: Cluster / Strategic | F25: Strategic Partnership | L25: NDA / Data Request | M25: Pass | N25: Active | O25: Medium | P25: Medium | Q25: High | R25: Cluster structuring & commercial model | S25: Advance cluster structuring with Transgrid/IBEDC; report weekly | T25: Temitope | W25: =IF(V25="","",TODAY()-V25) | X25: 0.3 | Y25: Strategic cluster/distribution opportunity under active structuring. | Z25: Yes | AA25: Technical, Legal, Strategy | AE25: =IF(AND(K25<>"",#REF!<>""),#REF!-K25,"") -> #REF!
AE26: =IF(AND(K26<>"",#REF!<>""),#REF!-K26,"") -> #REF!

Sheet Commercial Operations Tracker
A2: Commercial Operations Tracker — contracts, tariffs, renewals, KYC & customer issues
A3: Customer Name | B3: Business Line | C3: Contract Type | D3: Contract Start Date | E3: Contract Expiry Date | F3: Days to Expiry | G3: Renewal Status | H3: Tariff Review Date | I3: Tariff Escalation Status | J3: KYC Status | K3: Onboarding Status | L3: Current Commercial Issue | M3: Revenue Impact | N3: Operational Issue | O3: Customer Data Required | P3: Internal Owner | Q3: Escalation Point | R3: Next Action | S3: Due Date | T3: Priority | U3: Status | V3: Comment / Update
A4: Stanbic IBTC (WCC) | B4: Power | C4: PPA | D4: 45901 | F4: =IF($E4="","",$E4-TODAY()) | G4: Not Due | I4: Up to Date | J4: Complete | K4: Complete | M4: Low | P4: Commercial Ops | Q4: Commercial Manager (Mide) | R4: Document onboarding/KYC checklist (capture lessons) | T4: Low | U4: On Track | V4: Operating. Use as KYC/onboarding reference case.
A5: Sweetco Power | B5: Captive Power | C5: Captive Power Agreement | D5: 45901 | F5: =IF($E5="","",$E5-TODAY()) | G5: Overdue | I5: Overdue | J5: Complete | K5: Complete | L5: New contract & tariff escalation pending | M5: High | O5: Renewal terms & escalated tariff schedule | P5: Commercial Ops | Q5: Commercial Manager (Mide) | R5: Prepare contract renewal & tariff escalation plan | T5: High | U5: At Risk | V5: Contract expired; tariff escalation overdue. Priority renewal.
A6: Sweetco Gas | B6: Gas Retail | C6: GSPA | D6: 45901 | F6: =IF($E6="","",$E6-TODAY()) | G6: Not Due | I6: Up to Date | J6: Complete | K6: Complete | M6: Low | P6: Commercial Ops | Q6: Commercial Manager (Mide) | R6: Routine monitoring of volume offtake & billing | T6: Low | U6: On Track | V6: Operating.
A7: Starium Detergents FZE | B7: Gas Retail | C7: GSPA | D7: 45901 | F7: =IF($E7="","",$E7-TODAY()) | G7: Not Due | I7: Up to Date | J7: Complete | K7: Complete | M7: Low | P7: Commercial Ops | Q7: Commercial Manager (Mide) | R7: Routine monitoring of volume offtake & billing | T7: Low | U7: On Track | V7: Operating.
A8: Rumbu Industries Limited | B8: Gas Retail | C8: GSPA | D8: 45901 | F8: =IF($E8="","",$E8-TODAY()) | G8: Not Due | I8: Up to Date | J8: Complete | K8: Complete | M8: Low | P8: Commercial Ops | Q8: Commercial Manager (Mide) | R8: Routine monitoring of volume offtake & billing | T8: Low | U8: On Track | V8: Operating.
A9: Periwinkle Residences | B9: Power | C9: PPA | F9: =IF($E9="","",$E9-TODAY()) | G9: Not Due | I9: Up to Date | J9: Complete | K9: Complete | M9: Low | O9: Confirm contract start & tariff review dates | P9: Commercial Ops | Q9: Commercial Manager (Mide) | R9: Routine monitoring of consumption & billing | T9: Low | U9: On Track | V9: Operating.
A10: Orange Island Residences | B10: Power | C10: PPA | F10: =IF($E10="","",$E10-TODAY()) | G10: Not Due | I10: Up to Date | J10: Complete | K10: Complete | M10: Low | O10: Confirm contract start & tariff review dates | P10: Commercial Ops | Q10: Commercial Manager (Mide) | R10: Routine monitoring of consumption & billing | T10: Low | U10: On Track | V10: Operating.
A11: UBA PLC | B11: Power | C11: PPA (addendum in progress) | D11: 45901 | F11: =IF($E11="","",$E11-TODAY()) | G11: In Progress | I11: Under Review | J11: Complete | K11: Complete | L11: PPA addendum (tariff) under negotiation | M11: Medium | O11: Agreed addendum terms | P11: Commercial Ops | Q11: Commercial Manager (Mide) | R11: Conclude PPA addendum on tariff & commercial terms | T11: Medium | U11: In Progress | V11: Embedded plant live; commercial addendum in negotiation.

Sheet Gas Business Tracker
B2: Gas Business Tracker — Retail Gas, CNG & Autogas
B3: S/N | C3: Customer / Opportunity | D3: Plant / Solution Type | E3: Utilisation | F3: Opportunity Type | G3: Status | H3: Est. Vol (SCM/day) | I3: Commercial Operations Date | J3: Initiated Engagement (0.01) | K3: Reconnaissance Survey (0.02) | L3: Commercial Negotiations (0.15) | M3: Signed TermSheet (0.30) | N3: DED (0.40) | O3: Signed GSPA (0.60) | P3: Vendor Selection (0.70) | Q3: Connection Completed (0.90) | R3: Revenue Generation (1.00) | S3: Score | T3: Contract Status | U3: Contract Expiry | V3: Current Tariff | W3: Tariff Review Date | X3: Daily / Monthly Volume | Y3: Take-or-Pay Obligation | Z3: Payment Status | AA3: Operational Issue | AB3: Commercial Issue | AC3: Next Action | AD3: Owner | AE3: Due Date | AF3: Escalation Required? | AG3: Comments
B4: 1 | C4: Sweetco Gas | D4: Compressed Natural Gas | E4: Gas to Power and Heat | F4: Non-tender | G4: =IF(OR(S4=0,S4=""),"",IF(AND(S4>=0.01,S4<=0.15),"Early Stage",IF(S4<=0.4,"Mid Stage",IF(S4<=0.6,"Definitive Stage",IF(S4<=0.9,"Development Stage",IF(S4<=1,"Commercial Operations Stage","")))))) -> Commercial Operations Stage | I4: 45901 | J4: 0.01 | K4: 0.02 | L4: 0.15 | M4: 0.3 | N4: 0.4 | O4: 0.6 | P4: 0.7 | Q4: 0.9 | R4: 1 | S4: =IF(COUNT(J4:R4)=0,"",MAX(J4:R4)) -> 1 | T4: Active | Y4: Yes (confirm schedule) | Z4: Current | AC4: Monitor offtake & billing | AD4: Commercial Ops | AF4: No | AG4: Operating.
B5: 2 | C5: Starium Detergents FZE | D5: Compressed Natural Gas | E5: Gas to Power and Heat | F5: Non-tender | G5: =IF(OR(S5=0,S5=""),"",IF(AND(S5>=0.01,S5<=0.15),"Early Stage",IF(S5<=0.4,"Mid Stage",IF(S5<=0.6,"Definitive Stage",IF(S5<=0.9,"Development Stage",IF(S5<=1,"Commercial Operations Stage","")))))) -> Commercial Operations Stage | I5: 45901 | J5: 0.01 | K5: 0.02 | L5: 0.15 | M5: 0.3 | N5: 0.4 | O5: 0.6 | P5: 0.7 | Q5: 0.9 | R5: 1 | S5: =IF(COUNT(J5:R5)=0,"",MAX(J5:R5)) -> 1 | T5: Active | Z5: Current | AC5: Monitor offtake & billing | AD5: Commercial Ops | AF5: No | AG5: Operating.
B6: 3 | C6: Rumbu Industries Limited | D6: Compressed Natural Gas | E6: Gas to Power | F6: Non-tender | G6: =IF(OR(S6=0,S6=""),"",IF(AND(S6>=0.01,S6<=0.15),"Early Stage",IF(S6<=0.4,"Mid Stage",IF(S6<=0.6,"Definitive Stage",IF(S6<=0.9,"Development Stage",IF(S6<=1,"Commercial Operations Stage","")))))) -> Commercial Operations Stage | I6: 45901 | J6: 0.01 | K6: 0.02 | L6: 0.15 | M6: 0.3 | N6: 0.4 | O6: 0.6 | P6: 0.7 | Q6: 0.9 | R6: 1 | S6: =IF(COUNT(J6:R6)=0,"",MAX(J6:R6)) -> 1 | T6: Active | Z6: Current | AC6: Monitor offtake & billing | AD6: Commercial Ops | AF6: No | AG6: Operating.
B7: 4 | C7: Dangote | D7: Autogas | E7: Autogas | F7: Non-tender | G7: =IF(OR(S7=0,S7=""),"",IF(AND(S7>=0.01,S7<=0.15),"Early Stage",IF(S7<=0.4,"Mid Stage",IF(S7<=0.6,"Definitive Stage",IF(S7<=0.9,"Development Stage",IF(S7<=1,"Commercial Operations Stage","")))))) -> Definitive Stage | J7: 0.01 | K7: 0.02 | L7: 0.15 | M7: 0.3 | N7: 0.4 | O7: 0.6 | S7: =IF(COUNT(J7:R7)=0,"",MAX(J7:R7)) -> 0.6 | T7: In Negotiation | Z7: N/A | AC7: Advance with partner (Viathan) toward contract | AD7: BD Team | AF7: No | AG7: A new opportunity we are exploring with Viathan.
G8: =IF(OR(S8=0,S8=""),"",IF(AND(S8>=0.01,S8<=0.15),"Early Stage",IF(S8<=0.4,"Mid Stage",IF(S8<=0.6,"Definitive Stage",IF(S8<=0.9,"Development Stage",IF(S8<=1,"Commercial Operations Stage","")))))) | S8: =IF(COUNT(J8:R8)=0,"",MAX(J8:R8))

Sheet Power Business Tracker
B2: Power Business Tracker — Retail, Embedded & Captive Power
B3: S/N | C3: Customer / Opportunity | D3: Plant / Solution Type | E3: Energy Type | F3: Opportunity Type | G3: Status | H3: Est. Required Capacity (kW) | I3: Commercial Operations Date | J3: Initiated Engagement (0.01) | K3: Reconnaissance Survey (0.02) | L3: Energy Audit (0.03) | M3: Indicative FEED (0.05) | N3: Commercial Negotiations (0.15) | O3: Signed TermSheet / Award (0.30) | P3: DED (0.40) | Q3: Signed PPA (0.60) | R3: Vendor Selection (0.70) | S3: Connection Completed (0.90) | T3: Revenue Generation (1.00) | U3: Score | V3: Installed Capacity (kW) | W3: Contract Status | X3: Contract Expiry | Y3: Current Tariff | Z3: Tariff Review Date | AA3: Daily / Monthly Consumption | AB3: Metering Status | AC3: KYC Status | AD3: Onboarding Status | AE3: Operational Issue | AF3: Commercial Issue | AG3: Next Action | AH3: Owner | AI3: Due Date | AJ3: Escalation Required? | AK3: Comments
B4: 1 | C4: Stanbic IBTC (WCC) | D4: IPL-Embedded | E4: Gas | F4: Non-tender | G4: =IF(OR(U4=0,U4=""),"",IF(AND(U4>=0.01,U4<=0.15),"Early Stage",IF(U4<=0.4,"Mid Stage",IF(U4<=0.6,"Definitive Stage",IF(U4<=0.9,"Development Stage",IF(U4<=1,"Commercial Operations Stage","")))))) -> Commercial Operations Stage | H4: 750 | I4: 45901 | J4: 0.01 | K4: 0.02 | L4: 0.03 | M4: 0.05 | N4: 0.15 | O4: 0.3 | P4: 0.4 | Q4: 0.6 | R4: 0.7 | S4: 0.9 | T4: 1 | U4: =IF(COUNT(J4:T4)=0,"",MAX(J4:T4)) -> 1 | V4: 750 | W4: Active | AB4: Installed & Commissioned | AC4: Complete | AD4: Complete | AG4: Routine monitoring of consumption & billing | AH4: Commercial Ops | AJ4: No | AK4: Operating.
B5: 2 | C5: UBA PLC | D5: IPL-Embedded | E5: Gas | F5: Non-tender | G5: =IF(OR(U5=0,U5=""),"",IF(AND(U5>=0.01,U5<=0.15),"Early Stage",IF(U5<=0.4,"Mid Stage",IF(U5<=0.6,"Definitive Stage",IF(U5<=0.9,"Development Stage",IF(U5<=1,"Commercial Operations Stage","")))))) -> Development Stage | H5: 2700 | J5: 0.01 | K5: 0.02 | L5: 0.03 | M5: 0.05 | N5: 0.15 | O5: 0.3 | P5: 0.4 | Q5: 0.6 | R5: 0.7 | S5: 0.9 | U5: =IF(COUNT(J5:T5)=0,"",MAX(J5:T5)) -> 0.9 | W5: In Negotiation | AB5: Installed | AC5: Complete | AD5: In Progress | AG5: Advance to next stage gate | AH5: BD Team | AJ5: No | AK5: Negotiating addendum to the PPA (tariff & commercial).
B6: 3 | C6: Sterling Bank PLC | D6: IPL-Embedded | E6: Gas | F6: Non-tender | G6: =IF(OR(U6=0,U6=""),"",IF(AND(U6>=0.01,U6<=0.15),"Early Stage",IF(U6<=0.4,"Mid Stage",IF(U6<=0.6,"Definitive Stage",IF(U6<=0.9,"Development Stage",IF(U6<=1,"Commercial Operations Stage","")))))) -> Early Stage | H6: 750 | J6: 0.01 | K6: 0.02 | L6: 0.03 | M6: 0.05 | N6: 0.15 | U6: =IF(COUNT(J6:T6)=0,"",MAX(J6:T6)) -> 0.15 | W6: Not Started | AB6: Pending | AC6: In Progress | AD6: Not Started | AG6: Advance to next stage gate | AH6: BD Team | AJ6: No | AK6: Early-stage renegotiation; backup supply (~4hr); connected to IPL2.
B7: 4 | C7: Stanbic IBTC (Windsor Building) | D7: IPL-Embedded | E7: Gas | F7: Non-tender | G7: =IF(OR(U7=0,U7=""),"",IF(AND(U7>=0.01,U7<=0.15),"Early Stage",IF(U7<=0.4,"Mid Stage",IF(U7<=0.6,"Definitive Stage",IF(U7<=0.9,"Development Stage",IF(U7<=1,"Commercial Operations Stage","")))))) -> Early Stage | H7: 1000 | J7: 0.01 | K7: 0.02 | L7: 0.03 | M7: 0.05 | N7: 0.15 | U7: =IF(COUNT(J7:T7)=0,"",MAX(J7:T7)) -> 0.15 | W7: Not Started | AB7: Pending | AC7: In Progress | AD7: Not Started | AG7: Advance to next stage gate | AH7: BD Team | AJ7: No | AK7: Contract novation & commercial discussions in progress.
B8: 5 | C8: Periwinkle Residences | D8: PIPP-Embedded | E8: Gas | F8: Non-tender | G8: =IF(OR(U8=0,U8=""),"",IF(AND(U8>=0.01,U8<=0.15),"Early Stage",IF(U8<=0.4,"Mid Stage",IF(U8<=0.6,"Definitive Stage",IF(U8<=0.9,"Development Stage",IF(U8<=1,"Commercial Operations Stage","")))))) -> Commercial Operations Stage | H8: 250 | J8: 0.01 | K8: 0.02 | L8: 0.03 | M8: 0.05 | N8: 0.15 | O8: 0.3 | P8: 0.4 | Q8: 0.6 | R8: 0.7 | S8: 0.9 | T8: 1 | U8: =IF(COUNT(J8:T8)=0,"",MAX(J8:T8)) -> 1 | V8: 250 | W8: Active | AB8: Installed & Commissioned | AC8: Complete | AD8: Complete | AG8: Routine monitoring of consumption & billing | AH8: Commercial Ops | AJ8: No | AK8: Operating.
B9: 6 | C9: Orange Island Residences | D9: PIPP-Embedded | E9: Gas | F9: Non-tender | G9: =IF(OR(U9=0,U9=""),"",IF(AND(U9>=0.01,U9<=0.15),"Early Stage",IF(U9<=0.4,"Mid Stage",IF(U9<=0.6,"Definitive Stage",IF(U9<=0.9,"Development Stage",IF(U9<=1,"Commercial Operations Stage","")))))) -> Commercial Operations Stage | H9: 100 | J9: 0.01 | K9: 0.02 | L9: 0.03 | M9: 0.05 | N9: 0.15 | O9: 0.3 | P9: 0.4 | Q9: 0.6 | R9: 0.7 | S9: 0.9 | T9: 1 | U9: =IF(COUNT(J9:T9)=0,"",MAX(J9:T9)) -> 1 | V9: 100 | W9: Active | AB9: Installed & Commissioned | AC9: Complete | AD9: Complete | AG9: Routine monitoring of consumption & billing | AH9: Commercial Ops | AJ9: No | AK9: Operating.
B10: 7 | C10: Purple Mall | D10: PIPP-Embedded | E10: Gas | F10: Non-tender | G10: =IF(OR(U10=0,U10=""),"",IF(AND(U10>=0.01,U10<=0.15),"Early Stage",IF(U10<=0.4,"Mid Stage",IF(U10<=0.6,"Definitive Stage",IF(U10<=0.9,"Development Stage",IF(U10<=1,"Commercial Operations Stage","")))))) -> Mid Stage | H10: 500 | J10: 0.01 | K10: 0.02 | L10: 0.03 | M10: 0.05 | N10: 0.15 | O10: 0.3 | U10: =IF(COUNT(J10:T10)=0,"",MAX(J10:T10)) -> 0.3 | W10: In Negotiation | AB10: Pending | AC10: In Progress | AD10: Not Started | AG10: Advance to next stage gate | AH10: BD Team | AJ10: No | AK10: Commercial discussions in progress.
B11: 8 | C11: Sweetco Power | D11: Captive | E11: Gas | F11: Non-tender | G11: =IF(OR(U11=0,U11=""),"",IF(AND(U11>=0.01,U11<=0.15),"Early Stage",IF(U11<=0.4,"Mid Stage",IF(U11<=0.6,"Definitive Stage",IF(U11<=0.9,"Development Stage",IF(U11<=1,"Commercial Operations Stage","")))))) -> Commercial Operations Stage | H11: 1500 | I11: 45901 | J11: 0.01 | K11: 0.02 | L11: 0.03 | M11: 0.05 | N11: 0.15 | O11: 0.3 | P11: 0.4 | Q11: 0.6 | R11: 0.7 | S11: 0.9 | T11: 1 | U11: =IF(COUNT(J11:T11)=0,"",MAX(J11:T11)) -> 1 | V11: 1500 | W11: Expired | AB11: Installed & Commissioned | AC11: Complete | AD11: Complete | AG11: Routine monitoring of consumption & billing | AH11: Commercial Ops | AJ11: Yes | AK11: Operating. Contract renewal & tariff escalation due.
B12: 9 | C12: Renaissance | D12: IPL-Embedded | E12: Gas | F12: Non-tender | G12: =IF(OR(U12=0,U12=""),"",IF(AND(U12>=0.01,U12<=0.15),"Early Stage",IF(U12<=0.4,"Mid Stage",IF(U12<=0.6,"Definitive Stage",IF(U12<=0.9,"Development Stage",IF(U12<=1,"Commercial Operations Stage","")))))) -> Mid Stage | H12: 2000 | J12: 0.01 | K12: 0.02 | L12: 0.03 | M12: 0.05 | N12: 0.15 | O12: 0.3 | P12: 0.4 | U12: =IF(COUNT(J12:T12)=0,"",MAX(J12:T12)) -> 0.4 | W12: In Negotiation | AB12: Pending | AC12: In Progress | AD12: Not Started | AG12: Finalise & sign PPA | AH12: BD Team | AJ12: No | AK12: PPA to be signed in May 2026.
B13: 10 | C13: Re-insurance House | D13: IPL-Embedded | E13: Gas | F13: Non-tender | G13: =IF(OR(U13=0,U13=""),"",IF(AND(U13>=0.01,U13<=0.15),"Early Stage",IF(U13<=0.4,"Mid Stage",IF(U13<=0.6,"Definitive Stage",IF(U13<=0.9,"Development Stage",IF(U13<=1,"Commercial Operations Stage","")))))) -> Early Stage | H13: 3000 | J13: 0.01 | K13: 0.02 | L13: 0.03 | M13: 0.05 | N13: 0.15 | U13: =IF(COUNT(J13:T13)=0,"",MAX(J13:T13)) -> 0.15 | W13: Not Started | AB13: Pending | AC13: In Progress | AD13: Not Started | AG13: Advance to next stage gate | AH13: BD Team | AJ13: No | AK13: Energy audit completed; commercial discussions in progress.
B14: 11 | C14: Lekki Port | D14: Captive | E14: Gas | F14: Tender | G14: =IF(OR(U14=0,U14=""),"",IF(AND(U14>=0.01,U14<=0.15),"Early Stage",IF(U14<=0.4,"Mid Stage",IF(U14<=0.6,"Definitive Stage",IF(U14<=0.9,"Development Stage",IF(U14<=1,"Commercial Operations Stage","")))))) -> Early Stage | H14: 1000 | J14: 0.01 | K14: 0.02 | L14: 0.03 | M14: 0.05 | N14: 0.15 | U14: =IF(COUNT(J14:T14)=0,"",MAX(J14:T14)) -> 0.15 | W14: Not Started | AB14: Pending | AC14: In Progress | AD14: Not Started | AG14: Advance to next stage gate | AH14: BD Team | AJ14: No | AK14: Bid submission completed; technical alignment completed.
B15: 12 | C15: FCMB | D15: IPL-Embedded | E15: Gas | F15: Non-tender | G15: =IF(OR(U15=0,U15=""),"",IF(AND(U15>=0.01,U15<=0.15),"Early Stage",IF(U15<=0.4,"Mid Stage",IF(U15<=0.6,"Definitive Stage",IF(U15<=0.9,"Development Stage",IF(U15<=1,"Commercial Operations Stage","")))))) -> Early Stage | H15: 100000 | J15: 0.01 | K15: 0.02 | L15: 0.03 | M15: 0.05 | N15: 0.15 | U15: =IF(COUNT(J15:T15)=0,"",MAX(J15:T15)) -> 0.15 | W15: Not Started | AB15: Pending | AC15: In Progress | AD15: Not Started | AG15: Advance to next stage gate | AH15: BD Team | AJ15: No | AK15: Commercial discussions in progress.
B16: 13 | C16: NRC | D16: Captive | E16: Gas | F16: Non-tender | G16: =IF(OR(U16=0,U16=""),"",IF(AND(U16>=0.01,U16<=0.15),"Early Stage",IF(U16<=0.4,"Mid Stage",IF(U16<=0.6,"Definitive Stage",IF(U16<=0.9,"Development Stage",IF(U16<=1,"Commercial Operations Stage","")))))) -> Early Stage | H16: 6000 | J16: 0.01 | U16: =IF(COUNT(J16:T16)=0,"",MAX(J16:T16)) -> 0.01 | W16: Not Started | AB16: Pending | AC16: Not Started | AD16: Not Started | AG16: Advance to next stage gate | AH16: BD Team | AJ16: No | AK16: Stepped down.
B17: 14 | C17: Natcom | D17: IPL-Embedded | E17: Gas | F17: Non-tender | G17: =IF(OR(U17=0,U17=""),"",IF(AND(U17>=0.01,U17<=0.15),"Early Stage",IF(U17<=0.4,"Mid Stage",IF(U17<=0.6,"Definitive Stage",IF(U17<=0.9,"Development Stage",IF(U17<=1,"Commercial Operations Stage","")))))) -> Early Stage | H17: 200 | J17: 0.01 | K17: 0.02 | L17: 0.03 | U17: =IF(COUNT(J17:T17)=0,"",MAX(J17:T17)) -> 0.03 | W17: Not Started | AB17: Pending | AC17: Not Started | AD17: Not Started | AG17: Advance to next stage gate | AH17: BD Team | AJ17: No | AK17: Energy audit in progress.
B18: 15 | C18: Pillar Oil | D18: Captive | E18: Gas | F18: Non-tender | G18: =IF(OR(U18=0,U18=""),"",IF(AND(U18>=0.01,U18<=0.15),"Early Stage",IF(U18<=0.4,"Mid Stage",IF(U18<=0.6,"Definitive Stage",IF(U18<=0.9,"Development Stage",IF(U18<=1,"Commercial Operations Stage","")))))) -> Early Stage | H18: 200 | J18: 0.01 | K18: 0.02 | U18: =IF(COUNT(J18:T18)=0,"",MAX(J18:T18)) -> 0.02 | W18: Not Started | AB18: Pending | AC18: Not Started | AD18: Not Started | AG18: Advance to next stage gate | AH18: BD Team | AJ18: No | AK18: Techno-commercial discussions.
B19: 16 | C19: Tranquil and Quest Hospital | D19: PIPP-Embedded | E19: Gas | F19: Non-tender | G19: =IF(OR(U19=0,U19=""),"",IF(AND(U19>=0.01,U19<=0.15),"Early Stage",IF(U19<=0.4,"Mid Stage",IF(U19<=0.6,"Definitive Stage",IF(U19<=0.9,"Development Stage",IF(U19<=1,"Commercial Operations Stage","")))))) -> Early Stage | H19: 150 | J19: 0.01 | K19: 0.02 | U19: =IF(COUNT(J19:T19)=0,"",MAX(J19:T19)) -> 0.02 | W19: Not Started | AB19: Pending | AC19: Not Started | AD19: Not Started | AG19: Advance to next stage gate | AH19: BD Team | AJ19: No | AK19: Reconnaissance survey conducted.
B20: 17 | C20: Lakowe Resort | D20: Captive | E20: Gas | F20: Tender | G20: =IF(OR(U20=0,U20=""),"",IF(AND(U20>=0.01,U20<=0.15),"Early Stage",IF(U20<=0.4,"Mid Stage",IF(U20<=0.6,"Definitive Stage",IF(U20<=0.9,"Development Stage",IF(U20<=1,"Commercial Operations Stage","")))))) -> Early Stage | H20: 1000 | J20: 0.01 | U20: =IF(COUNT(J20:T20)=0,"",MAX(J20:T20)) -> 0.01 | W20: Not Started | AB20: Pending | AC20: Not Started | AD20: Not Started | AG20: Advance to next stage gate | AH20: BD Team | AJ20: No | AK20: Bid submission completed.
G21: =IF(OR(U21=0,U21=""),"",IF(AND(U21>=0.01,U21<=0.15),"Early Stage",IF(U21<=0.4,"Mid Stage",IF(U21<=0.6,"Definitive Stage",IF(U21<=0.9,"Development Stage",IF(U21<=1,"Commercial Operations Stage","")))))) | U21: =IF(COUNT(J21:T21)=0,"",MAX(J21:T21))
